pip-run.py
pip_run/__init__.py
pip_run/__main__.py
pip_run/commands.py
pip_run/deps.py
pip_run/launch.py
pip_run/read-deps.py
pip_run/scripts.py
pip_run/usage.txt
pip_run/compat/py310.py
pip_run/compat/py39.py
pip_run/retention/__init__.py
pip_run/retention/destroy.py
pip_run/retention/persist.py
pip_run-16.1.0.dist-info/licenses/LICENSE
pip_run-16.1.0.dist-info/METADATA
pip_run-16.1.0.dist-info/WHEEL
pip_run-16.1.0.dist-info/entry_points.txt
pip_run-16.1.0.dist-info/top_level.txt
pip_run-16.1.0.dist-info/RECORD
