Metadata-Version: 2.4
Name: pip-run
Version: 16.1.0
Summary: install packages and run Python with them
Author-email: "Jason R. Coombs" <jaraco@jaraco.com>
License-Expression: MIT
Project-URL: Source, https://github.com/jaraco/pip-run
Classifier: Development Status :: 5 - Production/Stable
Classifier: Intended Audience :: Developers
Classifier: Programming Language :: Python :: 3
Classifier: Programming Language :: Python :: 3 :: Only
Requires-Python: >=3.9
License-File: LICENSE
Requires-Dist: autocommand
Requires-Dist: path>=15.1
Requires-Dist: packaging
Requires-Dist: more_itertools>=8.3
Requires-Dist: jaraco.context
Requires-Dist: platformdirs
Requires-Dist: tomli; python_version < "3.11"
Requires-Dist: jaraco.functools>=3.7
Requires-Dist: jaraco.env
Requires-Dist: coherent.deps
Requires-Dist: tempora
Provides-Extra: test
Requires-Dist: pytest!=8.1.*,>=6; extra == "test"
Requires-Dist: nbformat; extra == "test"
Requires-Dist: pygments; extra == "test"
Requires-Dist: jaraco.path; extra == "test"
Requires-Dist: jaraco.test>=5.3; extra == "test"
Requires-Dist: flit-core; extra == "test"
Requires-Dist: pytest-freezer; extra == "test"
Provides-Extra: doc
Requires-Dist: sphinx>=3.5; extra == "doc"
Requires-Dist: jaraco.packaging>=9.3; extra == "doc"
Requires-Dist: rst.linker>=1.9; extra == "doc"
Requires-Dist: furo; extra == "doc"
Requires-Dist: sphinx-lint; extra == "doc"
Requires-Dist: jaraco.tidelift>=1.4; extra == "doc"
Provides-Extra: check
Requires-Dist: pytest-checkdocs>=2.4; extra == "check"
Requires-Dist: pytest-ruff>=0.2.1; sys_platform != "cygwin" and extra == "check"
Provides-Extra: cover
Requires-Dist: pytest-cov; extra == "cover"
Provides-Extra: enabler
Requires-Dist: pytest-enabler>=2.2; extra == "enabler"
Provides-Extra: type
Requires-Dist: pytest-mypy; extra == "type"
Requires-Dist: cowsay; extra == "type"
Dynamic: license-file
